nmslib.cpython-311-aarch64-linux-gnu.so
nmslib_nobrainz.libs/libgomp-a49a47f9.so.1.0.0
nmslib_nobrainz-2.1.2.dist-info/METADATA
nmslib_nobrainz-2.1.2.dist-info/WHEEL
nmslib_nobrainz-2.1.2.dist-info/top_level.txt
nmslib_nobrainz-2.1.2.dist-info/RECORD
nmslib_nobrainz-2.1.2.dist-info/licenses/LICENSE
nmslib_nobrainz-2.1.2.dist-info/licenses/LICENSE-Apache-2.0
nmslib_nobrainz-2.1.2.dist-info/sboms/auditwheel.cdx.json
