Metadata-Version: 2.4
Name: nmslib-nobrainz
Version: 2.1.2
Summary: Non-Metric Space Library (NMSLIB)
Home-page: https://github.com/notfoundsoft/nmslib
Author: B. Naidan, L. Boytsov, Yu. Malkov, B. Frederickson, D. Novak, et al.
Maintainer: notfoundsoft
Maintainer-email: notfoundsoft@gmail.com
Project-URL: Upstream (nmslib), https://github.com/nmslib/nmslib
Project-URL: Issues (this fork), https://github.com/notfoundsoft/nmslib/issues
License-File: LICENSE
License-File: LICENSE-Apache-2.0
Requires-Dist: pybind11>=2.2.3
Requires-Dist: scipy
Requires-Dist: numpy>=1.10.0; python_version >= "3.5"
Dynamic: author
Dynamic: description
Dynamic: home-page
Dynamic: license-file
Dynamic: maintainer
Dynamic: maintainer-email
Dynamic: project-url
Dynamic: requires-dist
Dynamic: summary
